pybloom/__init__.py
pybloom/example.py
pybloom/src/__init__.py
pybloom/src/bloomfilter.py
pybloom/src/backends/__init__.py
pybloom/src/backends/bitarraybackend.py
pybloom/src/backends/numpybackend.py
pybloom/src/backends/redisbackend.py
pybloom/tests/__init__.py
BloomFilterPy-1.1.dist-info/LICENSE
BloomFilterPy-1.1.dist-info/METADATA
BloomFilterPy-1.1.dist-info/WHEEL
BloomFilterPy-1.1.dist-info/top_level.txt
BloomFilterPy-1.1.dist-info/RECORD
